django_db_s3_backup/__init__.py
django_db_s3_backup/apps.py
django_db_s3_backup/exceptions.py
django_db_s3_backup/signals.py
django_db_s3_backup/utils.py
django_db_s3_backup/conf/__init__.py
django_db_s3_backup/conf/defaults.py
django_db_s3_backup/conf/settings.py
django_db_s3_backup/core/__init__.py
django_db_s3_backup/core/backup.py
django_db_s3_backup/core/operations.py
django_db_s3_backup/core/s3.py
django_db_s3_backup/core/scheduler.py
django_db_s3_backup/management/__init__.py
django_db_s3_backup/management/commands/__init__.py
django_db_s3_backup/management/commands/dbbackup.py
django_db_s3_backup-0.1.3.dist-info/licenses/LICENSE
django_db_s3_backup-0.1.3.dist-info/METADATA
django_db_s3_backup-0.1.3.dist-info/WHEEL
django_db_s3_backup-0.1.3.dist-info/top_level.txt
django_db_s3_backup-0.1.3.dist-info/RECORD
