Metadata-Version: 2.4
Name: django-db-s3-backup
Version: 0.1.3
Summary: Django database backup with S3 storage and scheduling
Home-page: https://github.com/Taofeeq97/postgreSQL_backup.git
Author: Otu Taofeeq
Author-email: otutaofeeqi@gmail.com
Keywords: django database backup s3_access
Classifier: Programming Language :: Python :: 3
Classifier: License :: OSI Approved :: MIT License
Classifier: Operating System :: OS Independent
Classifier: Framework :: Django
Classifier: Framework :: Django :: 3.2
Classifier: Framework :: Django :: 4.0
Requires-Python: >=3.7
License-File: LICENSE
Requires-Dist: Django>=3.2
Requires-Dist: boto3>=1.26.0
Requires-Dist: django-apscheduler>=0.6.2
Provides-Extra: dev
Requires-Dist: pytest>=6.0; extra == "dev"
Requires-Dist: pytest-django>=4.5.0; extra == "dev"
Requires-Dist: coverage>=6.0; extra == "dev"
Dynamic: author
Dynamic: author-email
Dynamic: classifier
Dynamic: description
Dynamic: description-content-type
Dynamic: home-page
Dynamic: keywords
Dynamic: license-file
Dynamic: provides-extra
Dynamic: requires-dist
Dynamic: requires-python
Dynamic: summary
